ocp_sso_token/__init__.py
ocp_sso_token/__main__.py
ocp_sso_token/kube_config.py
ocp_sso_token/ocp_oauth_login.py
ocp_sso_token-1.4.0.dist-info/licenses/LICENSE
ocp_sso_token-1.4.0.dist-info/METADATA
ocp_sso_token-1.4.0.dist-info/WHEEL
ocp_sso_token-1.4.0.dist-info/entry_points.txt
ocp_sso_token-1.4.0.dist-info/top_level.txt
ocp_sso_token-1.4.0.dist-info/RECORD
