Metadata-Version: 2.4
Name: ocp-sso-token
Version: 1.4.0
Summary: Obtain an OCP OAuth token for an SSO IdP with Kerberos support
Home-page: https://gitlab.com/cki-project/ocp-sso-token
Author: CKI Team
Author-email: cki-project@redhat.com
License: GPLv3
License-File: LICENSE
Requires-Dist: html5lib
Requires-Dist: PyYAML
Requires-Dist: requests
Requires-Dist: requests-gssapi
Provides-Extra: dev
Requires-Dist: mypy; extra == "dev"
Requires-Dist: responses; extra == "dev"
Requires-Dist: types-html5lib; extra == "dev"
Requires-Dist: types-PyYAML; extra == "dev"
Requires-Dist: types-requests; extra == "dev"
Provides-Extra: release
Requires-Dist: build; extra == "release"
Requires-Dist: twine; extra == "release"
Dynamic: license-file
